{
  "sevenDay": [
    {
      "Date": "2024-06-12",
      "Station_Code": "43025",
      "Station_Name": "Adilabad\r\n",
      "Today_Max_temp": null,
      "Today_Max_Departure_from_Normal": null,
      "Previous_Day_Max_temp": "41.3",
      "Previous_Day_Max_Departure_from_Normal": "3.4",
      "Today_Min_temp": "27.2",
      "Today_Min_Departure_from_Normal": "0.3",
      "Past_24_hrs_Rainfall": "NIL",
      "Relative_Humidity_at_0830": "71",
      "Relative_Humidity_at_1730": null,
      "Previous_Day_Relative_Humidity_at_1730": "54",
      "Sunset_time": "18:54",
      "Sunrise_time": "05:36",
      "Moonset_time": "23:43",
      "Moonrise_time": "10:43",
      "Todays_Forecast_Max_Temp": "39.0",
      "Todays_Forecast_Min_temp": "27.0",
      "Todays_Forecast": "Generally cloudy sky with Light rain",
      "Day_2_Max_Temp": "38.0",
      "Day_2_Min_temp": "24.0",
      "Day_2_Forecast": "Generally cloudy sky with Light rain",
      "Day_3_Max_Temp": "37.0",
      "Day_3_Min_temp": "24.0",
      "Day_3_Forecast": "Generally cloudy sky with one or two spells of rain or thundershowers",
      "Day_4_Max_Temp": "37.0",
      "Day_4_Min_temp": "25.0",
      "Day_4_Forecast": "Generally cloudy sky with one or two spells of rain or thundershowers",
      "Day_5_Max_Temp": "38.0",
      "Day_5_Min_temp": "24.0",
      "Day_5_Forecast": "Generally cloudy sky with Light rain",
      "Day_6_Max_Temp": "37.0",
      "Day_6_Min_temp": "23.0",
      "Day_6_Forecast": "Generally cloudy sky with possibility of rain or Thunderstorm",
      "Day_7_Max_Temp": "37.0",
      "Day_7_Min_temp": "23.0",
      "Day_7_Forecast": "Generally cloudy sky with possibility of rain or Thunderstorm",
      "Latitude": "19.6500",
      "Longitude": "78.5333"
    }
  ],
  "current": [
    {
      "Station Id": "43025",
      "Station": "Adilabad",
      "Date of Observation": "2024-06-12",
      "Time": "3",
      "Mean Sea Level Pressure": "1006",
      "Wind Direction": "320",
      "Wind Speed KMPH": "5.6",
      "Temperature": "28.8",
      "Weather Code": "0",
      "Nebulosity": "6",
      "Humidity": "71",
      "Last 24 hrs Rainfall": "0",
      "Feel Like": "32.5",
      "Sunrise": "05:37",
      "Sunset": "18:55",
      "Moonrise": "10:44",
      "Moonset": "23:44"
    }
  ]
}
